[
  {
    "count": 11,
    "expType": "object",
    "object": "2003_CC22_22S01",
    "filter": "R",
    "expTime": 120,
    "ra": 158.85583333333332,
    "dec": 12.080277777777777,
    "propid": "2022S-01",
    "priority": 4
  },
  {
    "count": 1,
    "expType": "object",
    "object": "445P_22S01",
    "filter": "R",
    "expTime": 120,
    "ra": 2.6858749999999993,
    "dec": 0.04769444444444444,
    "propid": "2022S-01",
    "priority": 3
  },
  {
    "count": 1,
    "expType": "object",
    "object": "C2022_R6_22S01",
    "filter": "R",
    "expTime": 120,
    "ra": 48.03254166666666,
    "dec": -41.32161111111112,
    "propid": "2022S-01",
    "priority": 3
  },
  {
    "count": 25,
    "expType": "object",
    "object": "157P_22S01",
    "filter": "R",
    "expTime": 30,
    "ra": 169.5773333333333,
    "dec": -8.064416666666668,
    "propid": "2022S-01",
    "priority": 4
  },
  {
    "count": 18,
    "expType": "object",
    "object": "2022_QE78_22S01",
    "filter": "R",
    "expTime": 60,
    "ra": 50.17245833333333,
    "dec": -19.8805,
    "propid": "2022S-01",
    "priority": 4
  },
  {
    "count": 30,
    "expType": "object",
    "object": "285P_22S01",
    "filter": "R",
    "expTime": 20,
    "ra": 338.46687499999996,
    "dec": -7.892333333333333,
    "propid": "2022S-01",
    "priority": 5
  },
  {
    "count": 4,
    "expType": "object",
    "object": "73P-JD001_22S01",
    "filter": "R",
    "expTime": 30,
    "ra": 355.9136666666666,
    "dec": -6.858805555555556,
    "propid": "2022S-01",
    "priority": 1
  },
  {
    "count": 25,
    "expType": "object",
    "object": "C2022_L2_22S01",
    "filter": "R",
    "expTime": 30,
    "ra": 275.3023333333333,
    "dec": 14.537555555555555,
    "propid": "2022S-01",
    "priority": 4
  },
  {
    "count": 0,
    "expType": "object",
    "object": "395P_22S01",
    "filter": "R",
    "expTime": 300,
    "ra": 351.66024999999996,
    "dec": -1.461361111111111,
    "propid": "2022S-01",
    "priority": 3
  },
  {
    "count": 1,
    "expType": "object",
    "object": "C2022_F1_22S01",
    "filter": "R",
    "expTime": 120,
    "ra": 317.37154166666664,
    "dec": -63.82152777777778,
    "propid": "2022S-01",
    "priority": 3
  },
  {
    "count": 25,
    "expType": "object",
    "object": "C2022_E2_22S01",
    "filter": "R",
    "expTime": 30,
    "ra": 154.641125,
    "dec": -19.84272222222222,
    "propid": "2022S-01",
    "priority": 5
  },
  {
    "count": 5,
    "expType": "object",
    "object": "81P_22S01",
    "filter": "R",
    "expTime": 20,
    "ra": 223.67499999999998,
    "dec": -14.139388888888888,
    "propid": "2022S-01",
    "priority": 1
  },
  {
    "count": 25,
    "expType": "object",
    "object": "C2022_A3_22S01",
    "filter": "R",
    "expTime": 30,
    "ra": 153.1894583333333,
    "dec": -0.54675,
    "propid": "2022S-01",
    "priority": 4
  },
  {
    "count": 30,
    "expType": "object",
    "object": "C2021_Y1_22S01",
    "filter": "R",
    "expTime": 20,
    "ra": 51.195874999999994,
    "dec": -6.237111111111111,
    "propid": "2022S-01",
    "priority": 6
  },
  {
    "count": 30,
    "expType": "object",
    "object": "C2021_G2_22S01",
    "filter": "R",
    "expTime": 20,
    "ra": 137.394,
    "dec": -38.94361111111111,
    "propid": "2022S-01",
    "priority": 5
  },
  {
    "count": 0,
    "expType": "object",
    "object": "97P_22S01",
    "filter": "R",
    "expTime": 300,
    "ra": 138.49954166666666,
    "dec": -3.833888888888889,
    "propid": "2022S-01",
    "priority": 3
  },
  {
    "count": 30,
    "expType": "object",
    "object": "C2021_T4_22S01",
    "filter": "R",
    "expTime": 20,
    "ra": 7.792166666666667,
    "dec": -13.755777777777778,
    "propid": "2022S-01",
    "priority": 5
  },
  {
    "count": 0,
    "expType": "object",
    "object": "C2021_T2_22S01",
    "filter": "R",
    "expTime": 300,
    "ra": 233.64824999999996,
    "dec": -16.246166666666667,
    "propid": "2022S-01",
    "priority": 3
  },
  {
    "count": 0,
    "expType": "object",
    "object": "382P_22S01",
    "filter": "R",
    "expTime": 300,
    "ra": 11.10970833333333,
    "dec": 0.37861111111111106,
    "propid": "2022S-01",
    "priority": 3
  },
  {
    "count": 30,
    "expType": "object",
    "object": "C2021_S3_22S01",
    "filter": "R",
    "expTime": 20,
    "ra": 83.97241666666665,
    "dec": -38.543305555555555,
    "propid": "2022S-01",
    "priority": 5
  },
  {
    "count": 0,
    "expType": "object",
    "object": "19P_22S01",
    "filter": "R",
    "expTime": 300,
    "ra": 219.68529166666664,
    "dec": 10.713305555555555,
    "propid": "2022S-01",
    "priority": 3
  },
  {
    "count": 0,
    "expType": "object",
    "object": "P2021_R1_22S01",
    "filter": "R",
    "expTime": 300,
    "ra": 33.093291666666666,
    "dec": 7.1465000000000005,
    "propid": "2022S-01",
    "priority": 3
  },
  {
    "count": 25,
    "expType": "object",
    "object": "C2021_P4_22S01",
    "filter": "R",
    "expTime": 30,
    "ra": 281.93375000000003,
    "dec": -65.01566666666666,
    "propid": "2022S-01",
    "priority": 5
  },
  {
    "count": 0,
    "expType": "object",
    "object": "386968_22S01",
    "filter": "R",
    "expTime": 300,
    "ra": 244.2099583333333,
    "dec": -22.566916666666668,
    "propid": "2022S-01",
    "priority": 3
  },
  {
    "count": 3,
    "expType": "object",
    "object": "C2014_UN271_22S01",
    "filter": "R",
    "expTime": 60,
    "ra": 37.050124999999994,
    "dec": -60.48491666666667,
    "propid": "2022S-01",
    "priority": 1
  },
  {
    "count": 0,
    "expType": "object",
    "object": "C2021_K2_22S01",
    "filter": "R",
    "expTime": 300,
    "ra": 276.99787499999996,
    "dec": 2.8580833333333335,
    "propid": "2022S-01",
    "priority": 3
  },
  {
    "count": 18,
    "expType": "object",
    "object": "99P_22S01",
    "filter": "R",
    "expTime": 60,
    "ra": 237.84066666666664,
    "dec": -21.73147222222222,
    "propid": "2022S-01",
    "priority": 4
  },
  {
    "count": 11,
    "expType": "object",
    "object": "22P_22S01",
    "filter": "R",
    "expTime": 120,
    "ra": 16.505666666666666,
    "dec": 1.6933055555555556,
    "propid": "2022S-01",
    "priority": 4
  },
  {
    "count": 30,
    "expType": "object",
    "object": "C2021_E3_22S01",
    "filter": "R",
    "expTime": 20,
    "ra": 123.66004166666663,
    "dec": -40.91791666666666,
    "propid": "2022S-01",
    "priority": 5
  },
  {
    "count": 25,
    "expType": "object",
    "object": "C2021_C5_22S01",
    "filter": "R",
    "expTime": 30,
    "ra": 223.71058333333332,
    "dec": -62.579750000000004,
    "propid": "2022S-01",
    "priority": 5
  },
  {
    "count": 1,
    "expType": "object",
    "object": "C2021_A9_22S01",
    "filter": "R",
    "expTime": 120,
    "ra": 128.19233333333332,
    "dec": 14.08988888888889,
    "propid": "2022S-01",
    "priority": 3
  },
  {
    "count": 1,
    "expType": "object",
    "object": "C2021_A1_22S01",
    "filter": "R",
    "expTime": 120,
    "ra": 257.5618333333333,
    "dec": -20.02702777777778,
    "propid": "2022S-01",
    "priority": 3
  },
  {
    "count": 0,
    "expType": "object",
    "object": "191P_22S01",
    "filter": "R",
    "expTime": 300,
    "ra": 171.33049999999997,
    "dec": 13.174166666666666,
    "propid": "2022S-01",
    "priority": 3
  },
  {
    "count": 0,
    "expType": "object",
    "object": "C2020_T2_22S01",
    "filter": "R",
    "expTime": 300,
    "ra": 345.13916666666665,
    "dec": -33.19069444444444,
    "propid": "2022S-01",
    "priority": 3
  },
  {
    "count": 30,
    "expType": "object",
    "object": "C2020_R7_22S01",
    "filter": "R",
    "expTime": 20,
    "ra": 267.263,
    "dec": -10.730722222222223,
    "propid": "2022S-01",
    "priority": 5
  },
  {
    "count": 18,
    "expType": "object",
    "object": "A2019_U5_22S01",
    "filter": "R",
    "expTime": 60,
    "ra": 207.33774999999997,
    "dec": 2.9644166666666667,
    "propid": "2022S-01",
    "priority": 4
  },
  {
    "count": 30,
    "expType": "object",
    "object": "C2019_L3_22S01",
    "filter": "R",
    "expTime": 20,
    "ra": 147.95412499999998,
    "dec": -31.979194444444442,
    "propid": "2022S-01",
    "priority": 6
  },
  {
    "count": 18,
    "expType": "object",
    "object": "C2019_F1_22S01",
    "filter": "R",
    "expTime": 60,
    "ra": 18.645291666666665,
    "dec": -17.757638888888888,
    "propid": "2022S-01",
    "priority": 4
  },
  {
    "count": 18,
    "expType": "object",
    "object": "C2019_E3_22S01",
    "filter": "R",
    "expTime": 60,
    "ra": 97.38616666666665,
    "dec": -76.57666666666667,
    "propid": "2022S-01",
    "priority": 4
  },
  {
    "count": 1,
    "expType": "object",
    "object": "2060_22S01",
    "filter": "R",
    "expTime": 120,
    "ra": 10.118124999999997,
    "dec": 6.248166666666667,
    "propid": "2022S-01",
    "priority": 3
  },
  {
    "count": 30,
    "expType": "object",
    "object": "C2017_K2_22S01",
    "filter": "R",
    "expTime": 20,
    "ra": 294.15304166666664,
    "dec": -67.91036111111111,
    "propid": "2022S-01",
    "priority": 6
  },
  {
    "count": 5,
    "expType": "object",
    "object": "73P_22S01",
    "filter": "R",
    "expTime": 20,
    "ra": 352.22649999999993,
    "dec": -12.1685,
    "propid": "2022S-01",
    "priority": 1
  },
  {
    "count": 0,
    "expType": "object",
    "object": "67P_22S01",
    "filter": "R",
    "expTime": 300,
    "ra": 210.33091666666667,
    "dec": -11.093388888888889,
    "propid": "2022S-01",
    "priority": 3
  }
]