[
  {
    "count": 1,
    "expType": "object",
    "object": "2003_CC22_22S01",
    "filter": "R",
    "expTime": 120,
    "ra": 157.6847083333333,
    "dec": 11.687527777777778,
    "propid": "2022S-01",
    "priority": 3
  },
  {
    "count": 0,
    "expType": "object",
    "object": "445P_22S01",
    "filter": "R",
    "expTime": 300,
    "ra": 353.35337499999997,
    "dec": -4.120416666666666,
    "propid": "2022S-01",
    "priority": 3
  },
  {
    "count": 1,
    "expType": "object",
    "object": "C2022_R6_22S01",
    "filter": "R",
    "expTime": 120,
    "ra": 49.63691666666666,
    "dec": -42.91808333333333,
    "propid": "2022S-01",
    "priority": 3
  },
  {
    "count": 25,
    "expType": "object",
    "object": "157P_22S01",
    "filter": "R",
    "expTime": 30,
    "ra": 164.85562499999995,
    "dec": -0.62375,
    "propid": "2022S-01",
    "priority": 4
  },
  {
    "count": 18,
    "expType": "object",
    "object": "2022_QE78_22S01",
    "filter": "R",
    "expTime": 60,
    "ra": 51.870625,
    "dec": -21.329444444444444,
    "propid": "2022S-01",
    "priority": 4
  },
  {
    "count": 30,
    "expType": "object",
    "object": "285P_22S01",
    "filter": "R",
    "expTime": 20,
    "ra": 317.60616666666664,
    "dec": -8.603944444444444,
    "propid": "2022S-01",
    "priority": 5
  },
  {
    "count": 1,
    "expType": "object",
    "object": "73P-BV_22S01",
    "filter": "R",
    "expTime": 120,
    "ra": 334.0431249999999,
    "dec": -21.67913888888889,
    "propid": "2022S-01",
    "priority": 1
  },
  {
    "count": 1,
    "expType": "object",
    "object": "73P-BU_22S01",
    "filter": "R",
    "expTime": 120,
    "ra": 336.1355,
    "dec": -20.882083333333334,
    "propid": "2022S-01",
    "priority": 1
  },
  {
    "count": 4,
    "expType": "object",
    "object": "73P-JD001_22S01",
    "filter": "R",
    "expTime": 30,
    "ra": 326.96166666666664,
    "dec": -23.43,
    "propid": "2022S-01",
    "priority": 1
  },
  {
    "count": 1,
    "expType": "object",
    "object": "395P_22S01",
    "filter": "R",
    "expTime": 120,
    "ra": 346.70104166666664,
    "dec": -3.163194444444444,
    "propid": "2022S-01",
    "priority": 3
  },
  {
    "count": 11,
    "expType": "object",
    "object": "C2022_F1_22S01",
    "filter": "R",
    "expTime": 120,
    "ra": 303.9616666666666,
    "dec": -68.43852777777778,
    "propid": "2022S-01",
    "priority": 4
  },
  {
    "count": 25,
    "expType": "object",
    "object": "C2022_E2_22S01",
    "filter": "R",
    "expTime": 30,
    "ra": 158.0105833333333,
    "dec": -19.985111111111113,
    "propid": "2022S-01",
    "priority": 4
  },
  {
    "count": 5,
    "expType": "object",
    "object": "81P_22S01",
    "filter": "R",
    "expTime": 20,
    "ra": 202.3488333333333,
    "dec": -7.634416666666667,
    "propid": "2022S-01",
    "priority": 1
  },
  {
    "count": 25,
    "expType": "object",
    "object": "C2022_A3_22S01",
    "filter": "R",
    "expTime": 30,
    "ra": 157.88774999999998,
    "dec": 3.7925555555555555,
    "propid": "2022S-01",
    "priority": 4
  },
  {
    "count": 30,
    "expType": "object",
    "object": "C2021_Y1_22S01",
    "filter": "R",
    "expTime": 20,
    "ra": 61.25758333333332,
    "dec": 7.255972222222222,
    "propid": "2022S-01",
    "priority": 6
  },
  {
    "count": 0,
    "expType": "object",
    "object": "A2021_X2_22S01",
    "filter": "R",
    "expTime": 300,
    "ra": 2.2834999999999996,
    "dec": -36.22488888888889,
    "propid": "2022S-01",
    "priority": 3
  },
  {
    "count": 25,
    "expType": "object",
    "object": "C2021_G2_22S01",
    "filter": "R",
    "expTime": 30,
    "ra": 138.7190833333333,
    "dec": -36.54097222222222,
    "propid": "2022S-01",
    "priority": 5
  },
  {
    "count": 0,
    "expType": "object",
    "object": "97P_22S01",
    "filter": "R",
    "expTime": 300,
    "ra": 140.37099999999998,
    "dec": -3.4280555555555554,
    "propid": "2022S-01",
    "priority": 3
  },
  {
    "count": 30,
    "expType": "object",
    "object": "C2021_T4_22S01",
    "filter": "R",
    "expTime": 20,
    "ra": 15.834999999999999,
    "dec": -12.886805555555554,
    "propid": "2022S-01",
    "priority": 5
  },
  {
    "count": 0,
    "expType": "object",
    "object": "C2021_T2_22S01",
    "filter": "R",
    "expTime": 300,
    "ra": 229.2014583333333,
    "dec": -19.136972222222223,
    "propid": "2022S-01",
    "priority": 3
  },
  {
    "count": 1,
    "expType": "object",
    "object": "382P_22S01",
    "filter": "R",
    "expTime": 120,
    "ra": 8.545166666666665,
    "dec": -0.6915555555555556,
    "propid": "2022S-01",
    "priority": 3
  },
  {
    "count": 30,
    "expType": "object",
    "object": "C2021_S3_22S01",
    "filter": "R",
    "expTime": 20,
    "ra": 90.17479166666666,
    "dec": -37.39213888888889,
    "propid": "2022S-01",
    "priority": 5
  },
  {
    "count": 0,
    "expType": "object",
    "object": "19P_22S01",
    "filter": "R",
    "expTime": 300,
    "ra": 212.84762499999997,
    "dec": 11.169138888888888,
    "propid": "2022S-01",
    "priority": 3
  },
  {
    "count": 0,
    "expType": "object",
    "object": "P2021_R1_22S01",
    "filter": "R",
    "expTime": 300,
    "ra": 33.25258333333333,
    "dec": 6.681972222222223,
    "propid": "2022S-01",
    "priority": 3
  },
  {
    "count": 30,
    "expType": "object",
    "object": "C2021_P4_22S01",
    "filter": "R",
    "expTime": 20,
    "ra": 246.49925,
    "dec": -62.317305555555556,
    "propid": "2022S-01",
    "priority": 5
  },
  {
    "count": 0,
    "expType": "object",
    "object": "386968_22S01",
    "filter": "R",
    "expTime": 300,
    "ra": 241.60175,
    "dec": -22.084305555555556,
    "propid": "2022S-01",
    "priority": 3
  },
  {
    "count": 3,
    "expType": "object",
    "object": "C2014_UN271_22S01",
    "filter": "R",
    "expTime": 60,
    "ra": 38.60629166666666,
    "dec": -61.32477777777778,
    "propid": "2022S-01",
    "priority": 1
  },
  {
    "count": 0,
    "expType": "object",
    "object": "C2021_K2_22S01",
    "filter": "R",
    "expTime": 300,
    "ra": 273.33537499999994,
    "dec": 0.6472777777777777,
    "propid": "2022S-01",
    "priority": 3
  },
  {
    "count": 11,
    "expType": "object",
    "object": "99P_22S01",
    "filter": "R",
    "expTime": 120,
    "ra": 230.42624999999995,
    "dec": -19.795444444444446,
    "propid": "2022S-01",
    "priority": 4
  },
  {
    "count": 18,
    "expType": "object",
    "object": "22P_22S01",
    "filter": "R",
    "expTime": 60,
    "ra": 12.154833333333332,
    "dec": -1.1635833333333332,
    "propid": "2022S-01",
    "priority": 4
  },
  {
    "count": 0,
    "expType": "object",
    "object": "7P_22S01",
    "filter": "R",
    "expTime": 300,
    "ra": 53.93274999999999,
    "dec": 1.855888888888889,
    "propid": "2022S-01",
    "priority": 3
  },
  {
    "count": 30,
    "expType": "object",
    "object": "C2021_E3_22S01",
    "filter": "R",
    "expTime": 20,
    "ra": 141.37704166666663,
    "dec": -43.97197222222223,
    "propid": "2022S-01",
    "priority": 5
  },
  {
    "count": 25,
    "expType": "object",
    "object": "C2021_C5_22S01",
    "filter": "R",
    "expTime": 30,
    "ra": 204.69374999999997,
    "dec": -53.80305555555555,
    "propid": "2022S-01",
    "priority": 5
  },
  {
    "count": 1,
    "expType": "object",
    "object": "C2021_A9_22S01",
    "filter": "R",
    "expTime": 120,
    "ra": 133.68779166666667,
    "dec": 13.636527777777777,
    "propid": "2022S-01",
    "priority": 3
  },
  {
    "count": 1,
    "expType": "object",
    "object": "C2021_A1_22S01",
    "filter": "R",
    "expTime": 120,
    "ra": 253.15249999999997,
    "dec": -20.5545,
    "propid": "2022S-01",
    "priority": 3
  },
  {
    "count": 0,
    "expType": "object",
    "object": "191P_22S01",
    "filter": "R",
    "expTime": 300,
    "ra": 170.117,
    "dec": 12.308833333333334,
    "propid": "2022S-01",
    "priority": 3
  },
  {
    "count": 0,
    "expType": "object",
    "object": "C2020_T2_22S01",
    "filter": "R",
    "expTime": 300,
    "ra": 340.7299583333333,
    "dec": -36.406194444444445,
    "propid": "2022S-01",
    "priority": 3
  },
  {
    "count": 30,
    "expType": "object",
    "object": "C2020_R7_22S01",
    "filter": "R",
    "expTime": 20,
    "ra": 261.9231666666666,
    "dec": -16.135277777777777,
    "propid": "2022S-01",
    "priority": 5
  },
  {
    "count": 11,
    "expType": "object",
    "object": "A2019_U5_22S01",
    "filter": "R",
    "expTime": 120,
    "ra": 208.0633333333333,
    "dec": 6.018611111111111,
    "propid": "2022S-01",
    "priority": 4
  },
  {
    "count": 30,
    "expType": "object",
    "object": "C2019_L3_22S01",
    "filter": "R",
    "expTime": 20,
    "ra": 150.12837499999998,
    "dec": -26.424,
    "propid": "2022S-01",
    "priority": 6
  },
  {
    "count": 25,
    "expType": "object",
    "object": "C2019_F1_22S01",
    "filter": "R",
    "expTime": 30,
    "ra": 19.103624999999997,
    "dec": -21.988833333333336,
    "propid": "2022S-01",
    "priority": 4
  },
  {
    "count": 18,
    "expType": "object",
    "object": "C2019_E3_22S01",
    "filter": "R",
    "expTime": 60,
    "ra": 113.69354166666665,
    "dec": -75.35544444444444,
    "propid": "2022S-01",
    "priority": 4
  },
  {
    "count": 1,
    "expType": "object",
    "object": "2060_22S01",
    "filter": "R",
    "expTime": 120,
    "ra": 10.048041666666665,
    "dec": 6.311055555555555,
    "propid": "2022S-01",
    "priority": 3
  },
  {
    "count": 30,
    "expType": "object",
    "object": "C2017_K2_22S01",
    "filter": "R",
    "expTime": 20,
    "ra": 261.7985833333333,
    "dec": -56.36383333333333,
    "propid": "2022S-01",
    "priority": 6
  },
  {
    "count": 5,
    "expType": "object",
    "object": "73P_22S01",
    "filter": "R",
    "expTime": 20,
    "ra": 333.82649999999995,
    "dec": -21.7435,
    "propid": "2022S-01",
    "priority": 1
  },
  {
    "count": 0,
    "expType": "object",
    "object": "67P_22S01",
    "filter": "R",
    "expTime": 300,
    "ra": 205.2439583333333,
    "dec": -9.169166666666666,
    "propid": "2022S-01",
    "priority": 3
  }
]