[
  {
    "count": 18,
    "expType": "object",
    "object": "2003_CC22_22S01",
    "filter": "R",
    "expTime": 60,
    "ra": 157.50629166666664,
    "dec": 13.241333333333332,
    "propid": "2022S-01",
    "priority": 4
  },
  {
    "count": 1,
    "expType": "object",
    "object": "445P_22S01",
    "filter": "R",
    "expTime": 120,
    "ra": 10.765125,
    "dec": 3.59675,
    "propid": "2022S-01",
    "priority": 3
  },
  {
    "count": 1,
    "expType": "object",
    "object": "C2022_R6_22S01",
    "filter": "R",
    "expTime": 120,
    "ra": 48.144041666666666,
    "dec": -39.45719444444445,
    "propid": "2022S-01",
    "priority": 3
  },
  {
    "count": 25,
    "expType": "object",
    "object": "157P_22S01",
    "filter": "R",
    "expTime": 30,
    "ra": 167.7319583333333,
    "dec": -11.356666666666666,
    "propid": "2022S-01",
    "priority": 4
  },
  {
    "count": 11,
    "expType": "object",
    "object": "2022_QE78_22S01",
    "filter": "R",
    "expTime": 120,
    "ra": 49.99654166666666,
    "dec": -18.186972222222224,
    "propid": "2022S-01",
    "priority": 4
  },
  {
    "count": 25,
    "expType": "object",
    "object": "285P_22S01",
    "filter": "R",
    "expTime": 30,
    "ra": 354.1623333333333,
    "dec": -5.723277777777778,
    "propid": "2022S-01",
    "priority": 5
  },
  {
    "count": 4,
    "expType": "object",
    "object": "73P-JD001_22S01",
    "filter": "R",
    "expTime": 30,
    "ra": 15.263374999999998,
    "dec": 6.29775,
    "propid": "2022S-01",
    "priority": 1
  },
  {
    "count": 4,
    "expType": "object",
    "object": "C2022_L2_22S01",
    "filter": "R",
    "expTime": 30,
    "ra": 277.55549999999994,
    "dec": 14.618861111111112,
    "propid": "2022S-01",
    "priority": 3
  },
  {
    "count": 0,
    "expType": "object",
    "object": "395P_22S01",
    "filter": "R",
    "expTime": 300,
    "ra": 356.4079583333333,
    "dec": 0.35241666666666666,
    "propid": "2022S-01",
    "priority": 3
  },
  {
    "count": 1,
    "expType": "object",
    "object": "C2022_F1_22S01",
    "filter": "R",
    "expTime": 120,
    "ra": 326.04866666666663,
    "dec": -60.71666666666667,
    "propid": "2022S-01",
    "priority": 3
  },
  {
    "count": 30,
    "expType": "object",
    "object": "C2022_E2_22S01",
    "filter": "R",
    "expTime": 20,
    "ra": 150.266875,
    "dec": -18.512027777777778,
    "propid": "2022S-01",
    "priority": 5
  },
  {
    "count": 5,
    "expType": "object",
    "object": "81P_22S01",
    "filter": "R",
    "expTime": 20,
    "ra": 238.47049999999996,
    "dec": -17.210305555555554,
    "propid": "2022S-01",
    "priority": 1
  },
  {
    "count": 25,
    "expType": "object",
    "object": "C2022_A3_22S01",
    "filter": "R",
    "expTime": 30,
    "ra": 146.66162500000002,
    "dec": -3.3931388888888887,
    "propid": "2022S-01",
    "priority": 5
  },
  {
    "count": 30,
    "expType": "object",
    "object": "C2021_Y1_22S01",
    "filter": "R",
    "expTime": 20,
    "ra": 48.80179166666667,
    "dec": -12.19663888888889,
    "propid": "2022S-01",
    "priority": 5
  },
  {
    "count": 30,
    "expType": "object",
    "object": "C2021_G2_22S01",
    "filter": "R",
    "expTime": 20,
    "ra": 135.19791666666666,
    "dec": -39.48708333333333,
    "propid": "2022S-01",
    "priority": 5
  },
  {
    "count": 0,
    "expType": "object",
    "object": "97P_22S01",
    "filter": "R",
    "expTime": 300,
    "ra": 135.02754166666665,
    "dec": -2.3835277777777777,
    "propid": "2022S-01",
    "priority": 3
  },
  {
    "count": 30,
    "expType": "object",
    "object": "C2021_T4_22S01",
    "filter": "R",
    "expTime": 20,
    "ra": 5.622791666666665,
    "dec": -13.17075,
    "propid": "2022S-01",
    "priority": 5
  },
  {
    "count": 0,
    "expType": "object",
    "object": "C2021_T2_22S01",
    "filter": "R",
    "expTime": 300,
    "ra": 234.99854166666665,
    "dec": -11.390055555555556,
    "propid": "2022S-01",
    "priority": 3
  },
  {
    "count": 0,
    "expType": "object",
    "object": "382P_22S01",
    "filter": "R",
    "expTime": 300,
    "ra": 14.58325,
    "dec": 1.8259444444444444,
    "propid": "2022S-01",
    "priority": 3
  },
  {
    "count": 30,
    "expType": "object",
    "object": "C2021_S3_22S01",
    "filter": "R",
    "expTime": 20,
    "ra": 80.15829166666666,
    "dec": -37.27972222222222,
    "propid": "2022S-01",
    "priority": 5
  },
  {
    "count": 0,
    "expType": "object",
    "object": "19P_22S01",
    "filter": "R",
    "expTime": 300,
    "ra": 222.59491666666665,
    "dec": 11.639722222222222,
    "propid": "2022S-01",
    "priority": 3
  },
  {
    "count": 25,
    "expType": "object",
    "object": "C2021_P4_22S01",
    "filter": "R",
    "expTime": 30,
    "ra": 304.13312499999995,
    "dec": -64.18719444444444,
    "propid": "2022S-01",
    "priority": 4
  },
  {
    "count": 0,
    "expType": "object",
    "object": "386968_22S01",
    "filter": "R",
    "expTime": 300,
    "ra": 245.704625,
    "dec": -22.842694444444444,
    "propid": "2022S-01",
    "priority": 3
  },
  {
    "count": 3,
    "expType": "object",
    "object": "C2014_UN271_22S01",
    "filter": "R",
    "expTime": 60,
    "ra": 36.964875,
    "dec": -59.592194444444445,
    "propid": "2022S-01",
    "priority": 1
  },
  {
    "count": 0,
    "expType": "object",
    "object": "C2021_K2_22S01",
    "filter": "R",
    "expTime": 300,
    "ra": 279.4514583333333,
    "dec": 5.090777777777777,
    "propid": "2022S-01",
    "priority": 3
  },
  {
    "count": 18,
    "expType": "object",
    "object": "99P_22S01",
    "filter": "R",
    "expTime": 60,
    "ra": 242.4560416666666,
    "dec": -22.84236111111111,
    "propid": "2022S-01",
    "priority": 4
  },
  {
    "count": 1,
    "expType": "object",
    "object": "22P_22S01",
    "filter": "R",
    "expTime": 120,
    "ra": 21.573916666666666,
    "dec": 4.310277777777777,
    "propid": "2022S-01",
    "priority": 3
  },
  {
    "count": 30,
    "expType": "object",
    "object": "C2021_E3_22S01",
    "filter": "R",
    "expTime": 20,
    "ra": 111.22858333333332,
    "dec": -33.60563888888889,
    "propid": "2022S-01",
    "priority": 5
  },
  {
    "count": 25,
    "expType": "object",
    "object": "C2021_C5_22S01",
    "filter": "R",
    "expTime": 30,
    "ra": 241.564875,
    "dec": -68.05236111111111,
    "propid": "2022S-01",
    "priority": 5
  },
  {
    "count": 1,
    "expType": "object",
    "object": "C2021_A9_22S01",
    "filter": "R",
    "expTime": 120,
    "ra": 123.32845833333333,
    "dec": 14.594138888888889,
    "propid": "2022S-01",
    "priority": 3
  },
  {
    "count": 1,
    "expType": "object",
    "object": "C2021_A1_22S01",
    "filter": "R",
    "expTime": 120,
    "ra": 259.8660833333333,
    "dec": -19.43875,
    "propid": "2022S-01",
    "priority": 3
  },
  {
    "count": 0,
    "expType": "object",
    "object": "191P_22S01",
    "filter": "R",
    "expTime": 300,
    "ra": 169.73795833333332,
    "dec": 14.779694444444445,
    "propid": "2022S-01",
    "priority": 3
  },
  {
    "count": 1,
    "expType": "object",
    "object": "C2020_U4_22S01",
    "filter": "R",
    "expTime": 120,
    "ra": 4.205583333333333,
    "dec": 14.656666666666666,
    "propid": "2022S-01",
    "priority": 3
  },
  {
    "count": 0,
    "expType": "object",
    "object": "C2020_T2_22S01",
    "filter": "R",
    "expTime": 300,
    "ra": 349.1537916666666,
    "dec": -30.966583333333332,
    "propid": "2022S-01",
    "priority": 3
  },
  {
    "count": 30,
    "expType": "object",
    "object": "C2020_R7_22S01",
    "filter": "R",
    "expTime": 20,
    "ra": 270.38512499999996,
    "dec": -5.954055555555556,
    "propid": "2022S-01",
    "priority": 5
  },
  {
    "count": 18,
    "expType": "object",
    "object": "A2019_U5_22S01",
    "filter": "R",
    "expTime": 60,
    "ra": 203.65779166666664,
    "dec": 1.24625,
    "propid": "2022S-01",
    "priority": 4
  },
  {
    "count": 30,
    "expType": "object",
    "object": "C2019_L3_22S01",
    "filter": "R",
    "expTime": 20,
    "ra": 144.31099999999998,
    "dec": -34.49063888888889,
    "propid": "2022S-01",
    "priority": 6
  },
  {
    "count": 18,
    "expType": "object",
    "object": "C2019_F1_22S01",
    "filter": "R",
    "expTime": 60,
    "ra": 19.917124999999995,
    "dec": -14.559555555555557,
    "propid": "2022S-01",
    "priority": 4
  },
  {
    "count": 18,
    "expType": "object",
    "object": "C2019_E3_22S01",
    "filter": "R",
    "expTime": 60,
    "ra": 85.57662499999999,
    "dec": -75.78777777777778,
    "propid": "2022S-01",
    "priority": 4
  },
  {
    "count": 1,
    "expType": "object",
    "object": "2060_22S01",
    "filter": "R",
    "expTime": 120,
    "ra": 10.677791666666666,
    "dec": 6.4206666666666665,
    "propid": "2022S-01",
    "priority": 3
  },
  {
    "count": 30,
    "expType": "object",
    "object": "C2017_K2_22S01",
    "filter": "R",
    "expTime": 20,
    "ra": 343.4201666666666,
    "dec": -70.27041666666666,
    "propid": "2022S-01",
    "priority": 6
  },
  {
    "count": 4,
    "expType": "object",
    "object": "73P_22S01",
    "filter": "R",
    "expTime": 30,
    "ra": 3.146791666666666,
    "dec": -6.159083333333334,
    "propid": "2022S-01",
    "priority": 1
  },
  {
    "count": 0,
    "expType": "object",
    "object": "67P_22S01",
    "filter": "R",
    "expTime": 300,
    "ra": 212.11779166666665,
    "dec": -11.75061111111111,
    "propid": "2022S-01",
    "priority": 3
  }
]