[
  {
    "count": 1,
    "expType": "object",
    "object": "2003_CC22_22S01",
    "filter": "R",
    "expTime": 120,
    "ra": 158.9065,
    "dec": 11.88163888888889,
    "propid": "2022S-01",
    "priority": 3
  },
  {
    "count": 1,
    "expType": "object",
    "object": "445P_22S01",
    "filter": "R",
    "expTime": 120,
    "ra": 0.6202916666666666,
    "dec": -0.8721944444444445,
    "propid": "2022S-01",
    "priority": 3
  },
  {
    "count": 1,
    "expType": "object",
    "object": "C2022_R6_22S01",
    "filter": "R",
    "expTime": 120,
    "ra": 48.20783333333333,
    "dec": -41.74938888888889,
    "propid": "2022S-01",
    "priority": 3
  },
  {
    "count": 25,
    "expType": "object",
    "object": "157P_22S01",
    "filter": "R",
    "expTime": 30,
    "ra": 169.26999999999998,
    "dec": -6.7827222222222225,
    "propid": "2022S-01",
    "priority": 4
  },
  {
    "count": 18,
    "expType": "object",
    "object": "2022_QE78_22S01",
    "filter": "R",
    "expTime": 60,
    "ra": 50.39420833333333,
    "dec": -20.266055555555557,
    "propid": "2022S-01",
    "priority": 4
  },
  {
    "count": 30,
    "expType": "object",
    "object": "285P_22S01",
    "filter": "R",
    "expTime": 20,
    "ra": 334.1770416666666,
    "dec": -8.273027777777779,
    "propid": "2022S-01",
    "priority": 5
  },
  {
    "count": 1,
    "expType": "object",
    "object": "73P-BV_22S01",
    "filter": "R",
    "expTime": 120,
    "ra": 348.92199999999997,
    "dec": -13.97713888888889,
    "propid": "2022S-01",
    "priority": 1
  },
  {
    "count": 1,
    "expType": "object",
    "object": "73P-BU_22S01",
    "filter": "R",
    "expTime": 120,
    "ra": 350.96762499999994,
    "dec": -12.943805555555556,
    "propid": "2022S-01",
    "priority": 1
  },
  {
    "count": 4,
    "expType": "object",
    "object": "73P-JD001_22S01",
    "filter": "R",
    "expTime": 30,
    "ra": 350.43887499999994,
    "dec": -10.44438888888889,
    "propid": "2022S-01",
    "priority": 1
  },
  {
    "count": 25,
    "expType": "object",
    "object": "C2022_L2_22S01",
    "filter": "R",
    "expTime": 30,
    "ra": 274.62966666666665,
    "dec": 14.670194444444444,
    "propid": "2022S-01",
    "priority": 4
  },
  {
    "count": 0,
    "expType": "object",
    "object": "395P_22S01",
    "filter": "R",
    "expTime": 300,
    "ra": 350.49804166666667,
    "dec": -1.8853888888888888,
    "propid": "2022S-01",
    "priority": 3
  },
  {
    "count": 1,
    "expType": "object",
    "object": "C2022_F1_22S01",
    "filter": "R",
    "expTime": 120,
    "ra": 314.8214583333333,
    "dec": -64.72525,
    "propid": "2022S-01",
    "priority": 3
  },
  {
    "count": 25,
    "expType": "object",
    "object": "C2022_E2_22S01",
    "filter": "R",
    "expTime": 30,
    "ra": 155.57416666666666,
    "dec": -20.000777777777778,
    "propid": "2022S-01",
    "priority": 5
  },
  {
    "count": 5,
    "expType": "object",
    "object": "81P_22S01",
    "filter": "R",
    "expTime": 20,
    "ra": 219.4337083333333,
    "dec": -13.023888888888889,
    "propid": "2022S-01",
    "priority": 1
  },
  {
    "count": 25,
    "expType": "object",
    "object": "C2022_A3_22S01",
    "filter": "R",
    "expTime": 30,
    "ra": 154.53824999999998,
    "dec": 0.30430555555555555,
    "propid": "2022S-01",
    "priority": 4
  },
  {
    "count": 30,
    "expType": "object",
    "object": "C2021_Y1_22S01",
    "filter": "R",
    "expTime": 20,
    "ra": 52.646499999999996,
    "dec": -4.007916666666667,
    "propid": "2022S-01",
    "priority": 6
  },
  {
    "count": 30,
    "expType": "object",
    "object": "C2021_G2_22S01",
    "filter": "R",
    "expTime": 20,
    "ra": 137.8478333333333,
    "dec": -38.5895,
    "propid": "2022S-01",
    "priority": 5
  },
  {
    "count": 0,
    "expType": "object",
    "object": "97P_22S01",
    "filter": "R",
    "expTime": 300,
    "ra": 139.21745833333333,
    "dec": -3.9694166666666666,
    "propid": "2022S-01",
    "priority": 3
  },
  {
    "count": 30,
    "expType": "object",
    "object": "C2021_T4_22S01",
    "filter": "R",
    "expTime": 20,
    "ra": 8.890666666666666,
    "dec": -13.781694444444446,
    "propid": "2022S-01",
    "priority": 5
  },
  {
    "count": 0,
    "expType": "object",
    "object": "C2021_T2_22S01",
    "filter": "R",
    "expTime": 300,
    "ra": 232.98558333333332,
    "dec": -16.907555555555554,
    "propid": "2022S-01",
    "priority": 3
  },
  {
    "count": 0,
    "expType": "object",
    "object": "382P_22S01",
    "filter": "R",
    "expTime": 300,
    "ra": 10.371083333333333,
    "dec": 0.0665,
    "propid": "2022S-01",
    "priority": 3
  },
  {
    "count": 30,
    "expType": "object",
    "object": "C2021_S3_22S01",
    "filter": "R",
    "expTime": 20,
    "ra": 85.22662499999998,
    "dec": -38.58561111111111,
    "propid": "2022S-01",
    "priority": 5
  },
  {
    "count": 0,
    "expType": "object",
    "object": "19P_22S01",
    "filter": "R",
    "expTime": 300,
    "ra": 218.54037499999998,
    "dec": 10.644361111111111,
    "propid": "2022S-01",
    "priority": 3
  },
  {
    "count": 0,
    "expType": "object",
    "object": "P2021_R1_22S01",
    "filter": "R",
    "expTime": 300,
    "ra": 32.88870833333333,
    "dec": 6.963305555555555,
    "propid": "2022S-01",
    "priority": 3
  },
  {
    "count": 25,
    "expType": "object",
    "object": "C2021_P4_22S01",
    "filter": "R",
    "expTime": 30,
    "ra": 275.0609583333333,
    "dec": -64.92325000000001,
    "propid": "2022S-01",
    "priority": 5
  },
  {
    "count": 0,
    "expType": "object",
    "object": "386968_22S01",
    "filter": "R",
    "expTime": 300,
    "ra": 243.72529166666666,
    "dec": -22.47822222222222,
    "propid": "2022S-01",
    "priority": 3
  },
  {
    "count": 3,
    "expType": "object",
    "object": "C2014_UN271_22S01",
    "filter": "R",
    "expTime": 60,
    "ra": 37.237625,
    "dec": -60.70033333333333,
    "propid": "2022S-01",
    "priority": 1
  },
  {
    "count": 0,
    "expType": "object",
    "object": "C2021_K2_22S01",
    "filter": "R",
    "expTime": 300,
    "ra": 276.26741666666663,
    "dec": 2.338277777777778,
    "propid": "2022S-01",
    "priority": 3
  },
  {
    "count": 11,
    "expType": "object",
    "object": "99P_22S01",
    "filter": "R",
    "expTime": 120,
    "ra": 236.42612499999998,
    "dec": -21.379833333333334,
    "propid": "2022S-01",
    "priority": 4
  },
  {
    "count": 11,
    "expType": "object",
    "object": "22P_22S01",
    "filter": "R",
    "expTime": 120,
    "ra": 15.35008333333333,
    "dec": 1.0309166666666667,
    "propid": "2022S-01",
    "priority": 4
  },
  {
    "count": 30,
    "expType": "object",
    "object": "C2021_E3_22S01",
    "filter": "R",
    "expTime": 20,
    "ra": 127.50579166666664,
    "dec": -42.19025,
    "propid": "2022S-01",
    "priority": 5
  },
  {
    "count": 25,
    "expType": "object",
    "object": "C2021_C5_22S01",
    "filter": "R",
    "expTime": 30,
    "ra": 219.44066666666666,
    "dec": -60.89402777777778,
    "propid": "2022S-01",
    "priority": 5
  },
  {
    "count": 1,
    "expType": "object",
    "object": "C2021_A9_22S01",
    "filter": "R",
    "expTime": 120,
    "ra": 129.44966666666667,
    "dec": 13.967166666666667,
    "propid": "2022S-01",
    "priority": 3
  },
  {
    "count": 1,
    "expType": "object",
    "object": "C2021_A1_22S01",
    "filter": "R",
    "expTime": 120,
    "ra": 256.7668333333333,
    "dec": -20.156777777777776,
    "propid": "2022S-01",
    "priority": 3
  },
  {
    "count": 0,
    "expType": "object",
    "object": "191P_22S01",
    "filter": "R",
    "expTime": 300,
    "ra": 171.3945833333333,
    "dec": 12.864916666666666,
    "propid": "2022S-01",
    "priority": 3
  },
  {
    "count": 0,
    "expType": "object",
    "object": "C2020_T2_22S01",
    "filter": "R",
    "expTime": 300,
    "ra": 344.128875,
    "dec": -33.82980555555556,
    "propid": "2022S-01",
    "priority": 3
  },
  {
    "count": 30,
    "expType": "object",
    "object": "C2020_R7_22S01",
    "filter": "R",
    "expTime": 20,
    "ra": 266.25612499999994,
    "dec": -11.898361111111111,
    "propid": "2022S-01",
    "priority": 5
  },
  {
    "count": 18,
    "expType": "object",
    "object": "A2019_U5_22S01",
    "filter": "R",
    "expTime": 60,
    "ra": 207.8039583333333,
    "dec": 3.5115555555555558,
    "propid": "2022S-01",
    "priority": 4
  },
  {
    "count": 30,
    "expType": "object",
    "object": "C2019_L3_22S01",
    "filter": "R",
    "expTime": 20,
    "ra": 148.68875,
    "dec": -31.01983333333333,
    "propid": "2022S-01",
    "priority": 6
  },
  {
    "count": 18,
    "expType": "object",
    "object": "C2019_F1_22S01",
    "filter": "R",
    "expTime": 60,
    "ra": 18.513833333333334,
    "dec": -18.637777777777778,
    "propid": "2022S-01",
    "priority": 4
  },
  {
    "count": 18,
    "expType": "object",
    "object": "C2019_E3_22S01",
    "filter": "R",
    "expTime": 60,
    "ra": 100.947625,
    "dec": -76.54488888888889,
    "propid": "2022S-01",
    "priority": 4
  },
  {
    "count": 1,
    "expType": "object",
    "object": "2060_22S01",
    "filter": "R",
    "expTime": 120,
    "ra": 10.037874999999998,
    "dec": 6.232722222222223,
    "propid": "2022S-01",
    "priority": 3
  },
  {
    "count": 30,
    "expType": "object",
    "object": "C2017_K2_22S01",
    "filter": "R",
    "expTime": 20,
    "ra": 284.8569166666667,
    "dec": -65.82283333333334,
    "propid": "2022S-01",
    "priority": 6
  },
  {
    "count": 5,
    "expType": "object",
    "object": "73P_22S01",
    "filter": "R",
    "expTime": 20,
    "ra": 348.9484166666666,
    "dec": -13.963277777777778,
    "propid": "2022S-01",
    "priority": 1
  },
  {
    "count": 0,
    "expType": "object",
    "object": "67P_22S01",
    "filter": "R",
    "expTime": 300,
    "ra": 209.52062499999997,
    "dec": -10.79438888888889,
    "propid": "2022S-01",
    "priority": 3
  }
]