[
  {
    "count": 18,
    "expType": "object",
    "object": "2003_CC22_22S01",
    "filter": "R",
    "expTime": 60,
    "ra": 157.31395833333332,
    "dec": 13.367277777777778,
    "propid": "2022S-01",
    "priority": 4
  },
  {
    "count": 1,
    "expType": "object",
    "object": "445P_22S01",
    "filter": "R",
    "expTime": 120,
    "ra": 11.505958333333334,
    "dec": 3.9164166666666667,
    "propid": "2022S-01",
    "priority": 3
  },
  {
    "count": 1,
    "expType": "object",
    "object": "C2022_R6_22S01",
    "filter": "R",
    "expTime": 120,
    "ra": 48.21133333333333,
    "dec": -39.27813888888889,
    "propid": "2022S-01",
    "priority": 3
  },
  {
    "count": 25,
    "expType": "object",
    "object": "157P_22S01",
    "filter": "R",
    "expTime": 30,
    "ra": 167.36599999999999,
    "dec": -11.521694444444446,
    "propid": "2022S-01",
    "priority": 4
  },
  {
    "count": 11,
    "expType": "object",
    "object": "2022_QE78_22S01",
    "filter": "R",
    "expTime": 120,
    "ra": 50.03124999999999,
    "dec": -18.022694444444443,
    "propid": "2022S-01",
    "priority": 4
  },
  {
    "count": 25,
    "expType": "object",
    "object": "285P_22S01",
    "filter": "R",
    "expTime": 30,
    "ra": 355.5312916666666,
    "dec": -5.487333333333333,
    "propid": "2022S-01",
    "priority": 5
  },
  {
    "count": 4,
    "expType": "object",
    "object": "73P-JD001_22S01",
    "filter": "R",
    "expTime": 30,
    "ra": 16.952916666666667,
    "dec": 7.420916666666667,
    "propid": "2022S-01",
    "priority": 1
  },
  {
    "count": 4,
    "expType": "object",
    "object": "C2022_L2_22S01",
    "filter": "R",
    "expTime": 30,
    "ra": 277.7260833333333,
    "dec": 14.667722222222222,
    "propid": "2022S-01",
    "priority": 3
  },
  {
    "count": 0,
    "expType": "object",
    "object": "395P_22S01",
    "filter": "R",
    "expTime": 300,
    "ra": 356.854625,
    "dec": 0.5278611111111111,
    "propid": "2022S-01",
    "priority": 3
  },
  {
    "count": 1,
    "expType": "object",
    "object": "C2022_F1_22S01",
    "filter": "R",
    "expTime": 120,
    "ra": 326.76262499999996,
    "dec": -60.46230555555556,
    "propid": "2022S-01",
    "priority": 3
  },
  {
    "count": 30,
    "expType": "object",
    "object": "C2022_E2_22S01",
    "filter": "R",
    "expTime": 20,
    "ra": 149.825,
    "dec": -18.333194444444445,
    "propid": "2022S-01",
    "priority": 5
  },
  {
    "count": 5,
    "expType": "object",
    "object": "81P_22S01",
    "filter": "R",
    "expTime": 20,
    "ra": 239.69324999999998,
    "dec": -17.40308333333333,
    "propid": "2022S-01",
    "priority": 1
  },
  {
    "count": 25,
    "expType": "object",
    "object": "C2022_A3_22S01",
    "filter": "R",
    "expTime": 30,
    "ra": 145.99325,
    "dec": -3.6149444444444447,
    "propid": "2022S-01",
    "priority": 5
  },
  {
    "count": 30,
    "expType": "object",
    "object": "C2021_Y1_22S01",
    "filter": "R",
    "expTime": 20,
    "ra": 48.798249999999996,
    "dec": -12.586222222222222,
    "propid": "2022S-01",
    "priority": 5
  },
  {
    "count": 30,
    "expType": "object",
    "object": "C2021_G2_22S01",
    "filter": "R",
    "expTime": 20,
    "ra": 134.9829583333333,
    "dec": -39.47338888888889,
    "propid": "2022S-01",
    "priority": 5
  },
  {
    "count": 0,
    "expType": "object",
    "object": "97P_22S01",
    "filter": "R",
    "expTime": 300,
    "ra": 134.69962499999997,
    "dec": -2.1937499999999996,
    "propid": "2022S-01",
    "priority": 3
  },
  {
    "count": 30,
    "expType": "object",
    "object": "C2021_T4_22S01",
    "filter": "R",
    "expTime": 20,
    "ra": 5.547999999999998,
    "dec": -13.09575,
    "propid": "2022S-01",
    "priority": 5
  },
  {
    "count": 0,
    "expType": "object",
    "object": "C2021_T2_22S01",
    "filter": "R",
    "expTime": 300,
    "ra": 234.99779166666664,
    "dec": -11.062750000000001,
    "propid": "2022S-01",
    "priority": 3
  },
  {
    "count": 0,
    "expType": "object",
    "object": "382P_22S01",
    "filter": "R",
    "expTime": 300,
    "ra": 14.938208333333332,
    "dec": 1.9713333333333334,
    "propid": "2022S-01",
    "priority": 3
  },
  {
    "count": 30,
    "expType": "object",
    "object": "C2021_S3_22S01",
    "filter": "R",
    "expTime": 20,
    "ra": 79.90899999999999,
    "dec": -37.097055555555556,
    "propid": "2022S-01",
    "priority": 5
  },
  {
    "count": 0,
    "expType": "object",
    "object": "19P_22S01",
    "filter": "R",
    "expTime": 300,
    "ra": 222.742625,
    "dec": 11.768166666666668,
    "propid": "2022S-01",
    "priority": 3
  },
  {
    "count": 25,
    "expType": "object",
    "object": "C2021_P4_22S01",
    "filter": "R",
    "expTime": 30,
    "ra": 305.8390416666666,
    "dec": -64.06169444444444,
    "propid": "2022S-01",
    "priority": 4
  },
  {
    "count": 0,
    "expType": "object",
    "object": "386968_22S01",
    "filter": "R",
    "expTime": 300,
    "ra": 245.81108333333333,
    "dec": -22.862861111111112,
    "propid": "2022S-01",
    "priority": 3
  },
  {
    "count": 3,
    "expType": "object",
    "object": "C2014_UN271_22S01",
    "filter": "R",
    "expTime": 60,
    "ra": 37.00216666666667,
    "dec": -59.51011111111111,
    "propid": "2022S-01",
    "priority": 1
  },
  {
    "count": 0,
    "expType": "object",
    "object": "C2021_K2_22S01",
    "filter": "R",
    "expTime": 300,
    "ra": 279.64275,
    "dec": 5.311833333333333,
    "propid": "2022S-01",
    "priority": 3
  },
  {
    "count": 18,
    "expType": "object",
    "object": "99P_22S01",
    "filter": "R",
    "expTime": 60,
    "ra": 242.810125,
    "dec": -22.926916666666667,
    "propid": "2022S-01",
    "priority": 4
  },
  {
    "count": 1,
    "expType": "object",
    "object": "22P_22S01",
    "filter": "R",
    "expTime": 120,
    "ra": 22.070124999999997,
    "dec": 4.548722222222222,
    "propid": "2022S-01",
    "priority": 3
  },
  {
    "count": 30,
    "expType": "object",
    "object": "C2021_E3_22S01",
    "filter": "R",
    "expTime": 20,
    "ra": 110.34783333333331,
    "dec": -32.82077777777778,
    "propid": "2022S-01",
    "priority": 5
  },
  {
    "count": 25,
    "expType": "object",
    "object": "C2021_C5_22S01",
    "filter": "R",
    "expTime": 30,
    "ra": 243.3067916666666,
    "dec": -68.46733333333333,
    "propid": "2022S-01",
    "priority": 5
  },
  {
    "count": 1,
    "expType": "object",
    "object": "C2021_A9_22S01",
    "filter": "R",
    "expTime": 120,
    "ra": 122.90125,
    "dec": 14.638805555555555,
    "propid": "2022S-01",
    "priority": 3
  },
  {
    "count": 0,
    "expType": "object",
    "object": "C2021_A1_22S01",
    "filter": "R",
    "expTime": 300,
    "ra": 260.01491666666664,
    "dec": -19.37847222222222,
    "propid": "2022S-01",
    "priority": 3
  },
  {
    "count": 0,
    "expType": "object",
    "object": "191P_22S01",
    "filter": "R",
    "expTime": 300,
    "ra": 169.50454166666665,
    "dec": 14.946055555555557,
    "propid": "2022S-01",
    "priority": 3
  },
  {
    "count": 1,
    "expType": "object",
    "object": "C2020_U4_22S01",
    "filter": "R",
    "expTime": 120,
    "ra": 4.237833333333333,
    "dec": 14.596333333333334,
    "propid": "2022S-01",
    "priority": 3
  },
  {
    "count": 0,
    "expType": "object",
    "object": "C2020_T2_22S01",
    "filter": "R",
    "expTime": 300,
    "ra": 349.52283333333327,
    "dec": -30.782444444444444,
    "propid": "2022S-01",
    "priority": 3
  },
  {
    "count": 30,
    "expType": "object",
    "object": "C2020_R7_22S01",
    "filter": "R",
    "expTime": 20,
    "ra": 270.6046666666667,
    "dec": -5.488944444444445,
    "propid": "2022S-01",
    "priority": 5
  },
  {
    "count": 18,
    "expType": "object",
    "object": "A2019_U5_22S01",
    "filter": "R",
    "expTime": 60,
    "ra": 203.15987499999997,
    "dec": 1.1152222222222223,
    "propid": "2022S-01",
    "priority": 4
  },
  {
    "count": 30,
    "expType": "object",
    "object": "C2019_L3_22S01",
    "filter": "R",
    "expTime": 20,
    "ra": 143.944875,
    "dec": -34.627833333333335,
    "propid": "2022S-01",
    "priority": 6
  },
  {
    "count": 18,
    "expType": "object",
    "object": "C2019_F1_22S01",
    "filter": "R",
    "expTime": 60,
    "ra": 20.079749999999997,
    "dec": -14.284416666666667,
    "propid": "2022S-01",
    "priority": 4
  },
  {
    "count": 18,
    "expType": "object",
    "object": "C2019_E3_22S01",
    "filter": "R",
    "expTime": 60,
    "ra": 84.71320833333331,
    "dec": -75.66072222222223,
    "propid": "2022S-01",
    "priority": 4
  },
  {
    "count": 1,
    "expType": "object",
    "object": "2060_22S01",
    "filter": "R",
    "expTime": 120,
    "ra": 10.74520833333333,
    "dec": 6.4439166666666665,
    "propid": "2022S-01",
    "priority": 3
  },
  {
    "count": 30,
    "expType": "object",
    "object": "C2017_K2_22S01",
    "filter": "R",
    "expTime": 20,
    "ra": 348.09637499999997,
    "dec": -69.8753611111111,
    "propid": "2022S-01",
    "priority": 6
  },
  {
    "count": 4,
    "expType": "object",
    "object": "73P_22S01",
    "filter": "R",
    "expTime": 30,
    "ra": 4.0435,
    "dec": -5.671111111111111,
    "propid": "2022S-01",
    "priority": 1
  },
  {
    "count": 0,
    "expType": "object",
    "object": "67P_22S01",
    "filter": "R",
    "expTime": 300,
    "ra": 212.17687499999997,
    "dec": -11.773611111111112,
    "propid": "2022S-01",
    "priority": 3
  }
]